safekorea/__init__.py
safekorea/py.typed
safekorea-0.1.0.dist-info/METADATA
safekorea-0.1.0.dist-info/WHEEL
safekorea-0.1.0.dist-info/RECORD
