Metadata-Version: 2.4
Name: safekorea
Version: 0.1.0
Summary: A tool for querying disaster information in South Korea
Author-email: Jx2H <admin@goton.kr>
Requires-Python: >=3.13
